pydbml/__init__.py
pydbml/constants.py
pydbml/database.py
pydbml/exceptions.py
pydbml/tools.py
pydbml/_classes/__init__.py
pydbml/_classes/base.py
pydbml/_classes/column.py
pydbml/_classes/enum.py
pydbml/_classes/expression.py
pydbml/_classes/index.py
pydbml/_classes/note.py
pydbml/_classes/project.py
pydbml/_classes/reference.py
pydbml/_classes/sticky_note.py
pydbml/_classes/table.py
pydbml/_classes/table_group.py
pydbml/classes/__init__.py
pydbml/definitions/__init__.py
pydbml/definitions/column.py
pydbml/definitions/common.py
pydbml/definitions/enum.py
pydbml/definitions/generic.py
pydbml/definitions/index.py
pydbml/definitions/project.py
pydbml/definitions/reference.py
pydbml/definitions/sticky_note.py
pydbml/definitions/table.py
pydbml/definitions/table_group.py
pydbml/parser/__init__.py
pydbml/parser/blueprints.py
pydbml/parser/parser.py
pydbml/renderer/__init__.py
pydbml/renderer/base.py
pydbml/renderer/dbml/__init__.py
pydbml/renderer/dbml/default/__init__.py
pydbml/renderer/dbml/default/column.py
pydbml/renderer/dbml/default/enum.py
pydbml/renderer/dbml/default/expression.py
pydbml/renderer/dbml/default/index.py
pydbml/renderer/dbml/default/note.py
pydbml/renderer/dbml/default/project.py
pydbml/renderer/dbml/default/reference.py
pydbml/renderer/dbml/default/renderer.py
pydbml/renderer/dbml/default/sticky_note.py
pydbml/renderer/dbml/default/table.py
pydbml/renderer/dbml/default/table_group.py
pydbml/renderer/dbml/default/utils.py
pydbml/renderer/sql/__init__.py
pydbml/renderer/sql/default/__init__.py
pydbml/renderer/sql/default/column.py
pydbml/renderer/sql/default/enum.py
pydbml/renderer/sql/default/expression.py
pydbml/renderer/sql/default/index.py
pydbml/renderer/sql/default/note.py
pydbml/renderer/sql/default/reference.py
pydbml/renderer/sql/default/renderer.py
pydbml/renderer/sql/default/table.py
pydbml/renderer/sql/default/utils.py
pydbml-1.2.0.dist-info/LICENSE
pydbml-1.2.0.dist-info/METADATA
pydbml-1.2.0.dist-info/WHEEL
pydbml-1.2.0.dist-info/top_level.txt
pydbml-1.2.0.dist-info/RECORD
